IOT_Analytics-0.0.2.dist-info/RECORD
IOT_Analytics-0.0.2.dist-info/top_level.txt
IOT_Analytics-0.0.2.dist-info/metadata.json
IOT_Analytics-0.0.2.dist-info/zip-safe
IOT_Analytics-0.0.2.dist-info/METADATA
IOT_Analytics-0.0.2.dist-info/DESCRIPTION.rst
IOT_Analytics-0.0.2.dist-info/WHEEL
iot_analytics/exceptions.py
iot_analytics/models.py
iot_analytics/__init__.py
iot_analytics/server/server.py
iot_analytics/server/utils.py
iot_analytics/server/__init__.py
iot_analytics/interfaces/api_interface.py
iot_analytics/interfaces/storage_interface.py
iot_analytics/interfaces/google_analytics_interface.py
iot_analytics/interfaces/__init__.py
iot_analytics/interfaces/file_storage_interface.py
iot_analytics/serializers/google_analytics.py
iot_analytics/serializers/__init__.py
iot_analytics/apps/__init__.py
iot_analytics/apps/zorg/drivers.py
iot_analytics/apps/zorg/__init__.py
iot_analytics/apps/zorg/adaptors/google_analytics.py
iot_analytics/apps/zorg/adaptors/__init__.py
tests/test_interfaces.py
tests/__init__.py
tests/zorg_app_tests/test_drivers.py
tests/zorg_app_tests/__init__.py
