Metadata-Version: 2.0
Name: IOT-Analytics
Version: 0.0.2
Summary: Flexable analytics for your robot or IOT device.
Home-page: https://github.com/gunthercox/iot-analytics
Author: Gunther Cox
Author-email: gunthercx@gmail.com
License: BSD
Keywords: iot,analytics
Platform: any
Classifier: Development Status :: 4 - Beta
Classifier: Intended Audience :: Developers
Classifier: License :: OSI Approved :: BSD License
Classifier: Environment :: Web Environment
Classifier: Operating System :: OS Independent
Classifier: Topic :: Software Development :: Libraries :: Python Modules
Classifier: Topic :: Internet
Classifier: Programming Language :: Python
Classifier: Programming Language :: Python :: 2.7
Classifier: Programming Language :: Python :: 3
Classifier: Programming Language :: Python :: 3.3
Classifier: Programming Language :: Python :: 3.4
Classifier: Programming Language :: Python :: 3.5
Requires-Dist: requests (<3.0.0)
Requires-Dist: tinydb (==3.1.0)
Requires-Dist: tornado (>=4.2.0)
Requires-Dist: tornado-cors (>=0.6.0)
Requires-Dist: zorg (>=0.0.1)
